{"De-Para":[
 {
  "codigoCurriculoAntigo": "TIN0117",
  "nomeCurriculoAntigo": "Administração Financeira",
  "codigoCurriculoNovo": "N\/A",
  "nomeCurriculoNovo": "N\/A"
 },
 {
  "codigoCurriculoAntigo": "TME0015",
  "nomeCurriculoAntigo": "Álgebra Linear",
  "codigoCurriculoNovo": "TMP0008",
  "nomeCurriculoNovo": "Álgebra Linear"
 },
 {
  "codigoCurriculoAntigo": "TIN0118",
  "nomeCurriculoAntigo": "Análise de Algoritmos",
  "codigoCurriculoNovo": "TMP0022",
  "nomeCurriculoNovo": "Projeto e Análise\nde Algoritmos"
 },
 {
  "codigoCurriculoAntigo": "TIN0108",
  "nomeCurriculoAntigo": "Análise de Sistemas",
  "codigoCurriculoNovo": "TMP0023",
  "nomeCurriculoNovo": "Análise e Projeto\nde Sistemas"
 },
 {
  "codigoCurriculoAntigo": "TIN0013",
  "nomeCurriculoAntigo": "Análise Empresarial e Administrativa",
  "codigoCurriculoNovo": "TMP0013",
  "nomeCurriculoNovo": "Fundamentos de\nGestão\nOrganizacional"
 },
 {
  "codigoCurriculoAntigo": "TIN0120",
  "nomeCurriculoAntigo": "Bancos de Dados I",
  "codigoCurriculoNovo": "TMP0027",
  "nomeCurriculoNovo": "Modelagem da\nInformação"
 },
 {
  "codigoCurriculoAntigo": "TIN0169",
  "nomeCurriculoAntigo": "Bancos de Dados II",
  "codigoCurriculoNovo": "TMP0028",
  "nomeCurriculoNovo": "Armazenamento e\nGestão de Dados"
 },
 {
  "codigoCurriculoAntigo": "TME0112",
  "nomeCurriculoAntigo": "Cálculo Diferencial e Integral I",
  "codigoCurriculoNovo": "TMP0009",
  "nomeCurriculoNovo": "Cálculo Diferencial\ne Integral I"
 },
 {
  "codigoCurriculoAntigo": "TME0113",
  "nomeCurriculoAntigo": "Cálculo Diferencial e Integral II",
  "codigoCurriculoNovo": "TMP0010",
  "nomeCurriculoNovo": "Cálculo Diferencial\ne Integral II"
 },
 {
  "codigoCurriculoAntigo": "TIN0106",
  "nomeCurriculoAntigo": "Desenvolvimento de Páginas WEB",
  "codigoCurriculoNovo": "TIN0106",
  "nomeCurriculoNovo": "Desenvolvimento de páginas web"
 },
 {
  "codigoCurriculoAntigo": "TIN0130",
  "nomeCurriculoAntigo": "Empreendedorismo",
  "codigoCurriculoNovo": "TMP0016",
  "nomeCurriculoNovo": "Empreendedorismo\ne Inovação"
 },
 {
  "codigoCurriculoAntigo": "TME0115",
  "nomeCurriculoAntigo": "Estatística",
  "codigoCurriculoNovo": "TMP0012",
  "nomeCurriculoNovo": "Estatística"
 },
 {
  "codigoCurriculoAntigo": "TIN0114",
  "nomeCurriculoAntigo": "Estruturas de Dados I",
  "codigoCurriculoNovo": "TMP0020",
  "nomeCurriculoNovo": "Estruturas de Dados"
 },
 {
  "codigoCurriculoAntigo": "TIN0168",
  "nomeCurriculoAntigo": "Estrutura de Dados II",
  "codigoCurriculoNovo": "TMP0053",
  "nomeCurriculoNovo": "Estruturas de\nDados\nAvançadas"
 },
 {
  "codigoCurriculoAntigo": "TIN0109",
  "nomeCurriculoAntigo": "Estruturas Discretas",
  "codigoCurriculoNovo": "TMP0054",
  "nomeCurriculoNovo": "Estruturas\nDiscretas com\nAlgoritmos"
 },
 {
  "codigoCurriculoAntigo": "TIN0112",
  "nomeCurriculoAntigo": "Fundamentos de Sistemas de Informação",
  "codigoCurriculoNovo": "TMP0001",
  "nomeCurriculoNovo": "Fundamentos de\nSistemas de\nInformação"
 },
 {
  "codigoCurriculoAntigo": "TIN0132",
  "nomeCurriculoAntigo": "Gerência de Projetos de Informática",
  "codigoCurriculoNovo": "TMP0026",
  "nomeCurriculoNovo": "Gerência de\nProjetos"
 },
 {
  "codigoCurriculoAntigo": "TIN0110",
  "nomeCurriculoAntigo": "Interação Humano-Computador",
  "codigoCurriculoNovo": "TMP0003",
  "nomeCurriculoNovo": "Interação Humano-Computador"
 },
 {
  "codigoCurriculoAntigo": "TIN0105",
  "nomeCurriculoAntigo": "Introdução à Lógica Computacional",
  "codigoCurriculoNovo": "TMP0018",
  "nomeCurriculoNovo": "Introdução à Lógica\nComputacional"
 },
 {
  "codigoCurriculoAntigo": "TIN0119",
  "nomeCurriculoAntigo": "Linguagens Formais e Autômatos",
  "codigoCurriculoNovo": "TMP0021",
  "nomeCurriculoNovo": "Linguagens e\nParadigmas de\nProgramação"
 },
 {
  "codigoCurriculoAntigo": "TME0011",
  "nomeCurriculoAntigo": "Matemática Básica",
  "codigoCurriculoNovo": "TMP0007",
  "nomeCurriculoNovo": "Fundamentos de\nCálculo"
 },
 {
  "codigoCurriculoAntigo": "TIN0108",
  "nomeCurriculoAntigo": "Organização de Computadores",
  "codigoCurriculoNovo": "TMP0030",
  "nomeCurriculoNovo": "Arquitetura de\nComputadores"
 },
 {
  "codigoCurriculoAntigo": "TME0114",
  "nomeCurriculoAntigo": "Probabilidade",
  "codigoCurriculoNovo": "TMP0011",
  "nomeCurriculoNovo": "Probabilidade"
 },
 {
  "codigoCurriculoAntigo": "TIN0122",
  "nomeCurriculoAntigo": "Processos de Software",
  "codigoCurriculoNovo": "N\/A",
  "nomeCurriculoNovo": "N\/A"
 },
 {
  "codigoCurriculoAntigo": "TIN0121",
  "nomeCurriculoAntigo": "Programação Modular",
  "codigoCurriculoNovo": "TMP0025",
  "nomeCurriculoNovo": "Engenharia de\nSoftware II"
 },
 {
  "codigoCurriculoAntigo": "TIN0131",
  "nomeCurriculoAntigo": "Projeto de Graduação I",
  "codigoCurriculoNovo": "TMP0033",
  "nomeCurriculoNovo": "Projeto de Graduação 1"
 },
 {
  "codigoCurriculoAntigo": "TIN0133",
  "nomeCurriculoAntigo": "Projeto de Graduação II",
  "codigoCurriculoNovo": "TMP0034",
  "nomeCurriculoNovo": "Projeto de Graduação 2"
 },
 {
  "codigoCurriculoAntigo": "TIN0171",
  "nomeCurriculoAntigo": "Projeto e Construção de Sistemas",
  "codigoCurriculoNovo": "TMP0024",
  "nomeCurriculoNovo": "Engenharia de\nSoftware I"
 },
 {
  "codigoCurriculoAntigo": "TIN0125",
  "nomeCurriculoAntigo": "Projeto e Construção de Sistemas com SGBD",
  "codigoCurriculoNovo": "TMP0005",
  "nomeCurriculoNovo": "Projeto Integrador II"
 },
 {
  "codigoCurriculoAntigo": "TIN0123",
  "nomeCurriculoAntigo": "Redes de Computadores I",
  "codigoCurriculoNovo": "TMP0032",
  "nomeCurriculoNovo": "Redes de\nComputadores"
 },
 {
  "codigoCurriculoAntigo": "TIN0126",
  "nomeCurriculoAntigo": "Redes de Computadores II",
  "codigoCurriculoNovo": "TMP0098",
  "nomeCurriculoNovo": "Redes Móveis e\nComputação\nUbíqua"
 },
 {
  "codigoCurriculoAntigo": "TIN0116",
  "nomeCurriculoAntigo": "Sistemas Operacionais",
  "codigoCurriculoNovo": "TMP0031",
  "nomeCurriculoNovo": "Sistemas\nOperacionais"
 },
 {
  "codigoCurriculoAntigo": "TIN0107",
  "nomeCurriculoAntigo": "Técnicas de Programação I",
  "codigoCurriculoNovo": "TMP0017",
  "nomeCurriculoNovo": "Algoritmos e\nProgramação"
 },
 {
  "codigoCurriculoAntigo": "TIN0107",
  "nomeCurriculoAntigo": "Técnicas de Programação I",
  "codigoCurriculoNovo": "TMP0004",
  "nomeCurriculoNovo": "Projeto Integrador I"
 },
 {
  "codigoCurriculoAntigo": "TIN0011",
  "nomeCurriculoAntigo": "Técnicas de Programação II",
  "codigoCurriculoNovo": "TMP0019",
  "nomeCurriculoNovo": "Técnicas de\nProgramação"
 },
 {
  "codigoCurriculoAntigo": "HTD0058",
  "nomeCurriculoAntigo": "Teorias e Práticas Discursivas",
  "codigoCurriculoNovo": "N\/A",
  "nomeCurriculoNovo": "N\/A"
 },
 {
  "codigoCurriculoAntigo": "TIN0054",
  "nomeCurriculoAntigo": "Atividades Curriculares de Extensão 1",
  "codigoCurriculoNovo": "N\/A",
  "nomeCurriculoNovo": "N\/A"
 },
 {
  "codigoCurriculoAntigo": "TIN0055",
  "nomeCurriculoAntigo": "Atividades Curriculares de Extensão 2",
  "codigoCurriculoNovo": "N\/A",
  "nomeCurriculoNovo": "N\/A"
 },
 {
  "codigoCurriculoAntigo": "TIN0056",
  "nomeCurriculoAntigo": "Atividades Curriculares de Extensão 3",
  "codigoCurriculoNovo": "N\/A",
  "nomeCurriculoNovo": "N\/A"
 },
 {
  "codigoCurriculoAntigo": "TIN0057",
  "nomeCurriculoAntigo": "Atividades Curriculares de Extensão 4",
  "codigoCurriculoNovo": "N\/A",
  "nomeCurriculoNovo": "N\/A"
 },
 {
  "codigoCurriculoAntigo": "TIN0151",
  "nomeCurriculoAntigo": "Formação Complementar 1",
  "codigoCurriculoNovo": "TIN0151",
  "nomeCurriculoNovo": "Formação Complementar I"
 },
 {
  "codigoCurriculoAntigo": "TIN0152",
  "nomeCurriculoAntigo": "Formação Complementar 2",
  "codigoCurriculoNovo": "TIN0152",
  "nomeCurriculoNovo": "Formação Complementar II"
 },
 {
  "codigoCurriculoAntigo": "TIN0153",
  "nomeCurriculoAntigo": "Formação Complementar 3",
  "codigoCurriculoNovo": "N\/A",
  "nomeCurriculoNovo": "N\/A"
 },
 {
  "codigoCurriculoAntigo": "TIN0154",
  "nomeCurriculoAntigo": "Formação Complementar 4",
  "codigoCurriculoNovo": "N\/A",
  "nomeCurriculoNovo": "N\/A"
 },
 {
  "codigoCurriculoAntigo": "TIN0135",
  "nomeCurriculoAntigo": "Administração de Bancos de Dados",
  "codigoCurriculoNovo": "TIN0135",
  "nomeCurriculoNovo": "Administração\nde Banco de\nDados"
 },
 {
  "codigoCurriculoAntigo": "TIN0144",
  "nomeCurriculoAntigo": "Algoritmos para Problemas Combinatórios",
  "codigoCurriculoNovo": "TIN0144",
  "nomeCurriculoNovo": "Algoritmos para Problemas Combinatórios"
 },
 {
  "codigoCurriculoAntigo": "TIN0150",
  "nomeCurriculoAntigo": "Ambiente Operacional UNIX",
  "codigoCurriculoNovo": "TIN0150",
  "nomeCurriculoNovo": "Ambiente\nOperacional\nUNIX"
 },
 {
  "codigoCurriculoAntigo": "TIN0146",
  "nomeCurriculoAntigo": "Compiladores",
  "codigoCurriculoNovo": "N\/A",
  "nomeCurriculoNovo": "N\/A"
 },
 {
  "codigoCurriculoAntigo": "TIN0149",
  "nomeCurriculoAntigo": "Computação Gráfica",
  "codigoCurriculoNovo": "N\/A",
  "nomeCurriculoNovo": "N\/A"
 },
 {
  "codigoCurriculoAntigo": "TIN0138",
  "nomeCurriculoAntigo": "Comunicação e Segurança de Dados",
  "codigoCurriculoNovo": "TMP0099",
  "nomeCurriculoNovo": "Segurança de\nTecnologia da\nInformação"
 },
 {
  "codigoCurriculoAntigo": "TIN0158",
  "nomeCurriculoAntigo": "Desenvolvimento de Servidor WEB",
  "codigoCurriculoNovo": "TMP0068",
  "nomeCurriculoNovo": "Desenvolvimento\nde Servidor Web"
 },
 {
  "codigoCurriculoAntigo": "TIN0143",
  "nomeCurriculoAntigo": "Fluxos em Redes",
  "codigoCurriculoNovo": "TMP0056",
  "nomeCurriculoNovo": "Fluxos em\nRedes"
 },
 {
  "codigoCurriculoAntigo": "TIN0147",
  "nomeCurriculoAntigo": "Fundamentos de Representação de Conhecimento e Raciocínio",
  "codigoCurriculoNovo": "TIN0147",
  "nomeCurriculoNovo": "Fundamentos de\nRepresentação\nde\nConhecimento e\nRaciocínio"
 },
 {
  "codigoCurriculoAntigo": "TIN0136",
  "nomeCurriculoAntigo": "Gerência de dados em Ambientes Distribuídos e Paralelos",
  "codigoCurriculoNovo": "N\/A",
  "nomeCurriculoNovo": "N\/A"
 },
 {
  "codigoCurriculoAntigo": "TIN0160",
  "nomeCurriculoAntigo": "Gestão de Processos de Negócios",
  "codigoCurriculoNovo": "TMP0014",
  "nomeCurriculoNovo": "Gestão de\nProcessos de\nNegócios"
 },
 {
  "codigoCurriculoAntigo": "TIN0128",
  "nomeCurriculoAntigo": "Informática na Educação",
  "codigoCurriculoNovo": "TMP0038",
  "nomeCurriculoNovo": "Informática na Educação"
 },
 {
  "codigoCurriculoAntigo": "TIN0172",
  "nomeCurriculoAntigo": "Inteligência Artificial",
  "codigoCurriculoNovo": "TMP0058",
  "nomeCurriculoNovo": "Introdução à\nInteligência\nArtificial"
 },
 {
  "codigoCurriculoAntigo": "TIN0142",
  "nomeCurriculoAntigo": "Programação Linear",
  "codigoCurriculoNovo": "TIN0142",
  "nomeCurriculoNovo": "Programação Linear"
 },
 {
  "codigoCurriculoAntigo": "TIN0159",
  "nomeCurriculoAntigo": "Sistemas Colaborativos",
  "codigoCurriculoNovo": "TIN0159",
  "nomeCurriculoNovo": "Sistemas Colaborativos"
 },
 {
  "codigoCurriculoAntigo": "TIN0148",
  "nomeCurriculoAntigo": "Sistemas Multimídia",
  "codigoCurriculoNovo": "N\/A",
  "nomeCurriculoNovo": "N\/A"
 },
 {
  "codigoCurriculoAntigo": "TIN0145",
  "nomeCurriculoAntigo": "Tópicos Avançados em Algoritmos I",
  "codigoCurriculoNovo": "TMP0063",
  "nomeCurriculoNovo": "Tópicos em\nAlgoritmos"
 },
 {
  "codigoCurriculoAntigo": "TIN0137",
  "nomeCurriculoAntigo": "Tópicos Avançados em Bancos de Dados I",
  "codigoCurriculoNovo": "N\/A",
  "nomeCurriculoNovo": "N\/A"
 },
 {
  "codigoCurriculoAntigo": "TIN0162",
  "nomeCurriculoAntigo": "Tópicos Avançados em Bancos de Dados II",
  "codigoCurriculoNovo": "N\/A",
  "nomeCurriculoNovo": "N\/A"
 },
 {
  "codigoCurriculoAntigo": "TIN0163",
  "nomeCurriculoAntigo": "Tópicos Avançados em Bancos de Dados III",
  "codigoCurriculoNovo": "N\/A",
  "nomeCurriculoNovo": "N\/A"
 },
 {
  "codigoCurriculoAntigo": "TIN0161",
  "nomeCurriculoAntigo": "Tópicos Avançados em Engenharia de Software I",
  "codigoCurriculoNovo": "N\/A",
  "nomeCurriculoNovo": "N\/A"
 },
 {
  "codigoCurriculoAntigo": "TIN0166",
  "nomeCurriculoAntigo": "Tópicos Avançados em Engenharia de Software II",
  "codigoCurriculoNovo": "N\/A",
  "nomeCurriculoNovo": "N\/A"
 },
 {
  "codigoCurriculoAntigo": "TIN0141",
  "nomeCurriculoAntigo": "Tópicos Avançados em Redes de Computadores I",
  "codigoCurriculoNovo": "N\/A",
  "nomeCurriculoNovo": "N\/A"
 },
 {
  "codigoCurriculoAntigo": "TIN0164",
  "nomeCurriculoAntigo": "Tópicos Avançados em Redes de Computadores II",
  "codigoCurriculoNovo": "N\/A",
  "nomeCurriculoNovo": "N\/A"
 },
 {
  "codigoCurriculoAntigo": "TIN0165",
  "nomeCurriculoAntigo": "Tópicos Avançados em Redes de Computadores III",
  "codigoCurriculoNovo": "N\/A",
  "nomeCurriculoNovo": "N\/A"
 },
 {
  "codigoCurriculoAntigo": "HDI0164",
  "nomeCurriculoAntigo": "Culturas\nAfro-Brasileiras em\nSala de Aula",
  "codigoCurriculoNovo": "HDI0164",
  "nomeCurriculoNovo": "Culturas\nAfro-Brasileiras\nem Sala de Aula"
 },
 {
  "codigoCurriculoAntigo": "SER0012",
  "nomeCurriculoAntigo": "Educação\nAmbiental e\nCidadania",
  "codigoCurriculoNovo": "SER0012",
  "nomeCurriculoNovo": "Educação\nAmbiental e\nCidadania"
 },
 {
  "codigoCurriculoAntigo": "HDI0142",
  "nomeCurriculoAntigo": "Língua Brasileira de Sinais",
  "codigoCurriculoNovo": "HDI0142",
  "nomeCurriculoNovo": "Língua Brasileira de Sinais"
 }
]
}